profile_readme/__init__.py
profile_readme/__main__.py
profile_readme/cli.py
profile_readme/generator.py
profile_readme/github.py
profile_readme/init.py
profile_readme/utils.py
profile_readme-0.1.2.dist-info/LICENSE
profile_readme-0.1.2.dist-info/METADATA
profile_readme-0.1.2.dist-info/WHEEL
profile_readme-0.1.2.dist-info/entry_points.txt
profile_readme-0.1.2.dist-info/top_level.txt
profile_readme-0.1.2.dist-info/RECORD
