Metadata-Version: 2.1
Name: profile-readme
Version: 0.1.2
Summary: A CLI tool for generating a GitHub profile README using the Jinja2 template engine.
Home-page: https://github.com/Robert-96/profile-readme
Author: Robert-96
Author-email: dezmereanrobert@gmail.com
License: MIT
Project-URL: Bug Tracker, https://github.com/Robert-96/profile-readme/issues/
Project-URL: Documentation, https://profile-readme.rtfd.io/
Project-URL: Source, https://github.com/Robert-96/profile-readme/
Keywords: profile-readme,github,profile,readme
Platform: UNKNOWN
Classifier: Development Status :: 4 - Beta
Classifier: Intended Audience :: Developers
Classifier: Intended Audience :: Other Audience
Classifier: Environment :: Console
Classifier: License :: OSI Approved :: MIT License
Classifier: Programming Language :: Cython
Classifier: Programming Language :: Python :: Implementation
Classifier: Programming Language :: Python :: Implementation :: CPython
Classifier: Programming Language :: Python :: Implementation :: PyPy
Classifier: Programming Language :: Python :: 3 :: Only
Classifier: Programming Language :: Python :: 3.4
Classifier: Programming Language :: Python :: 3.5
Classifier: Programming Language :: Python :: 3.6
Classifier: Programming Language :: Python :: 3.7
Classifier: Programming Language :: Python :: 3.8
Classifier: Programming Language :: Python :: 3.9
Classifier: Operating System :: OS Independent
Classifier: Topic :: Software Development :: Libraries
Classifier: Topic :: Text Processing
Classifier: Topic :: Text Processing :: Markup :: HTML
Classifier: Topic :: Text Processing :: Markup :: Markdown
Classifier: Topic :: Utilities
Requires-Python: >=3.4.0
Requires-Dist: click
Requires-Dist: click-help-colors
Requires-Dist: requests
Requires-Dist: requests-cache
Requires-Dist: jinja2
Requires-Dist: python-dotenv
Requires-Dist: python-dateutil
